odoo/addons/mrp_stock_move_actual_date/README.rst
odoo/addons/mrp_stock_move_actual_date/__init__.py
odoo/addons/mrp_stock_move_actual_date/__manifest__.py
odoo/addons/mrp_stock_move_actual_date/i18n/mrp_stock_move_actual_date.pot
odoo/addons/mrp_stock_move_actual_date/models/__init__.py
odoo/addons/mrp_stock_move_actual_date/models/mrp_production.py
odoo/addons/mrp_stock_move_actual_date/models/mrp_unbuild.py
odoo/addons/mrp_stock_move_actual_date/readme/CONTRIBUTORS.rst
odoo/addons/mrp_stock_move_actual_date/readme/DESCRIPTION.rst
odoo/addons/mrp_stock_move_actual_date/static/description/icon.png
odoo/addons/mrp_stock_move_actual_date/static/description/index.html
odoo/addons/mrp_stock_move_actual_date/tests/__init__.py
odoo/addons/mrp_stock_move_actual_date/tests/test_mrp_stock_move_actual_date.py
odoo/addons/mrp_stock_move_actual_date/views/mrp_production_views.xml
odoo/addons/mrp_stock_move_actual_date/views/mrp_unbuild_views.xml
odoo_addon_mrp_stock_move_actual_date-16.0.1.0.0.2.dist-info/METADATA
odoo_addon_mrp_stock_move_actual_date-16.0.1.0.0.2.dist-info/WHEEL
odoo_addon_mrp_stock_move_actual_date-16.0.1.0.0.2.dist-info/top_level.txt
odoo_addon_mrp_stock_move_actual_date-16.0.1.0.0.2.dist-info/RECORD
